{
  "NewEleven_Dashboard Products Group by ASIN_01_09_2025-01_09_2025_(19_16_01_878).xlsx": {
    "path": "C:/Users/admin1/Desktop/Performance-Tracking/Agg-SB/H2_2025_US\\Tháng 9\\NewEleven_Dashboard Products Group by ASIN_01_09_2025-01_09_2025_(19_16_01_878).xlsx",
    "date": "2025-09-01",
    "hash": "b27fa0cf13b61153b569f7794c3caa05",
    "modification_time": 1757297763.9856634,
    "processed_at": "2025-09-10 12:56:22.078029"
  },
  "NewEleven_Dashboard Products Group by ASIN_02_09_2025-02_09_2025_(19_16_15_662).xlsx": {
    "path": "C:/Users/admin1/Desktop/Performance-Tracking/Agg-SB/H2_2025_US\\Tháng 9\\NewEleven_Dashboard Products Group by ASIN_02_09_2025-02_09_2025_(19_16_15_662).xlsx",
    "date": "2025-09-02",
    "hash": "056e1855f219f3c0b5278d1cea7872f3",
    "modification_time": 1757297777.053551,
    "processed_at": "2025-09-10 12:56:22.103341"
  },
  "NewEleven_Dashboard Products Group by ASIN_03_09_2025-03_09_2025_(19_16_29_823).xlsx": {
    "path": "C:/Users/admin1/Desktop/Performance-Tracking/Agg-SB/H2_2025_US\\Tháng 9\\NewEleven_Dashboard Products Group by ASIN_03_09_2025-03_09_2025_(19_16_29_823).xlsx",
    "date": "2025-09-03",
    "hash": "8deb7d7f1735f4bb29069244fa9d5d7f",
    "modification_time": 1757297793.3807378,
    "processed_at": "2025-09-10 12:56:22.128706"
  },
  "NewEleven_Dashboard Products Group by ASIN_04_09_2025-04_09_2025_(19_16_43_260).xlsx": {
    "path": "C:/Users/admin1/Desktop/Performance-Tracking/Agg-SB/H2_2025_US\\Tháng 9\\NewEleven_Dashboard Products Group by ASIN_04_09_2025-04_09_2025_(19_16_43_260).xlsx",
    "date": "2025-09-04",
    "hash": "2162f1a29410c2948d49b18f40214b99",
    "modification_time": 1757297805.2534041,
    "processed_at": "2025-09-10 12:56:22.151443"
  },
  "NewEleven_Dashboard Products Group by ASIN_05_09_2025-05_09_2025_(19_16_56_451).xlsx": {
    "path": "C:/Users/admin1/Desktop/Performance-Tracking/Agg-SB/H2_2025_US\\Tháng 9\\NewEleven_Dashboard Products Group by ASIN_05_09_2025-05_09_2025_(19_16_56_451).xlsx",
    "date": "2025-09-05",
    "hash": "b297656877e91eaf928cfb5b96f724ca",
    "modification_time": 1757297819.737662,
    "processed_at": "2025-09-10 12:56:22.175854"
  },
  "NewEleven_Dashboard Products Group by ASIN_06_09_2025-06_09_2025_(19_17_10_882).xlsx": {
    "path": "C:/Users/admin1/Desktop/Performance-Tracking/Agg-SB/H2_2025_US\\Tháng 9\\NewEleven_Dashboard Products Group by ASIN_06_09_2025-06_09_2025_(19_17_10_882).xlsx",
    "date": "2025-09-06",
    "hash": "15bd42c92bcc16b371c59286cb74b838",
    "modification_time": 1757297831.8747675,
    "processed_at": "2025-09-10 12:56:22.198164"
  },
  "NewEleven_Dashboard Products Group by ASIN_07_09_2025-07_09_2025_(19_23_49_683).xlsx": {
    "path": "C:/Users/admin1/Desktop/Performance-Tracking/Agg-SB/H2_2025_US\\Tháng 9\\NewEleven_Dashboard Products Group by ASIN_07_09_2025-07_09_2025_(19_23_49_683).xlsx",
    "date": "2025-09-07",
    "hash": "d9bbd75f72a794e118aca7d06a1c4f1c",
    "modification_time": 1757384631.5327692,
    "processed_at": "2025-09-10 12:56:22.226817"
  },
  "NewEleven_Dashboard Products Group by ASIN_08_09_2025-08_09_2025_(22_37_30_899).xlsx": {
    "path": "C:/Users/admin1/Desktop/Performance-Tracking/Agg-SB/H2_2025_US\\Tháng 9\\NewEleven_Dashboard Products Group by ASIN_08_09_2025-08_09_2025_(22_37_30_899).xlsx",
    "date": "2025-09-08",
    "hash": "5984875eeff9c2b758ba4cadf7a61d50",
    "modification_time": 1757482653.0935495,
    "processed_at": "2025-09-10 12:56:22.251090"
  },
  "NewEleven_Dashboard Products Group by ASIN_09_09_2025-09_09_2025_(22_33_44_315).xlsx": {
    "path": "C:/Users/admin1/Desktop/Performance-Tracking/Agg-SB/H2_2025_US\\Tháng 9\\NewEleven_Dashboard Products Group by ASIN_09_09_2025-09_09_2025_(22_33_44_315).xlsx",
    "date": "2025-09-09",
    "hash": "87140e7eaae4f9c43bf0cf0ca1031e9a",
    "modification_time": 1757482425.3701763,
    "processed_at": "2025-09-10 12:56:22.269842"
  }
}